{
 "f": [
  {
   "__tuple__": true, 
   "items": [
    "", 
    0, 
    2147483647, 
    "code_explorer_custom_root_folder_name"
   ]
  }, 
  {
   "__tuple__": true, 
   "items": [
    "/2147483647", 
    0, 
    "-S46EXZrEe+W3M9IC1V7u4", 
    "\u82f1\u96c4"
   ]
  }, 
  {
   "__tuple__": true, 
   "items": [
    "/2147483647", 
    1, 
    "-Z5DXXZrEe+enM9IC1V7u3", 
    "\u521b\u751f\u7269"
   ]
  }, 
  {
   "__tuple__": true, 
   "items": [
    "/2147483647", 
    4, 
    "OmlnWXc0Ee+5MLVju2zWk5", 
    "\u81ea\u5b9a\u4e49"
   ]
  }, 
  {
   "__tuple__": true, 
   "items": [
    "/2147483647", 
    5, 
    "+dRcfXphEe+GV0EgHb22v9", 
    "\u7ec3\u529f\u623f"
   ]
  }, 
  {
   "__tuple__": true, 
   "items": [
    "/2147483647", 
    6, 
    "+duHXnphEe+UlEEgHb22v9", 
    "\u5173\u5361"
   ]
  }, 
  {
   "__tuple__": true, 
   "items": [
    "/2147483647", 
    7, 
    "+fztLHphEe+GmEEgHb22v7", 
    "\u4e3b\u7ebf"
   ]
  }, 
  {
   "__tuple__": true, 
   "items": [
    "/2147483647", 
    8, 
    "+iKYIHphEe+HekEgHb22v0", 
    "\u4e5d\u5c42\u5996\u5854"
   ]
  }, 
  {
   "__tuple__": true, 
   "items": [
    "/2147483647/+iKYIHphEe+HekEgHb22v0", 
    0, 
    "+iKYIXphEe+KfEEgHb22vy", 
    "\u738b\u7684\u5a01\u5149(2)"
   ]
  }, 
  {
   "__tuple__": true, 
   "items": [
    "/2147483647/+iKYIHphEe+HekEgHb22v0", 
    1, 
    "+iVW3XphEe+0jUEgHb22vy", 
    "\u5fa1\u524d\u536b\u58eb"
   ]
  }, 
  {
   "__tuple__": true, 
   "items": [
    "/2147483647/+iKYIHphEe+HekEgHb22v0", 
    2, 
    "+ia2NHphEe+wp0EgHb22v+", 
    "\u5438\u8840\u9b3c\u5bb6\u65cf"
   ]
  }, 
  {
   "__tuple__": true, 
   "items": [
    "/2147483647/+iKYIHphEe+HekEgHb22v0", 
    3, 
    "+ir7V3phEe+4H0EgHb22vy", 
    "\u53cc\u5b50\u70bc\u72f1\u9b54(2)"
   ]
  }, 
  {
   "__tuple__": true, 
   "items": [
    "/2147483647/+iKYIHphEe+HekEgHb22v0", 
    4, 
    "+i26DXphEe+yhkEgHb22vw", 
    "\u7194\u5ca9\u6d1e\u7a9f"
   ]
  }, 
  {
   "__tuple__": true, 
   "items": [
    "/2147483647/+iKYIHphEe+HekEgHb22v0", 
    5, 
    "+jB4zXphEe+Vb0EgHb22v7", 
    "\u90aa\u6076\u517d\u4eba"
   ]
  }, 
  {
   "__tuple__": true, 
   "items": [
    "/2147483647/+iKYIHphEe+HekEgHb22v0", 
    6, 
    "+jNek3phEe+4HkEgHb22v-", 
    "\u5e7d\u9b42\u6bbf"
   ]
  }, 
  {
   "__tuple__": true, 
   "items": [
    "/2147483647/+iKYIHphEe+HekEgHb22v0", 
    7, 
    "+jYdTnphEe+4EkEgHb22vw", 
    "\u57cb\u5c38\u5730"
   ]
  }, 
  {
   "__tuple__": true, 
   "items": [
    "/2147483647/+iKYIHphEe+HekEgHb22v0", 
    8, 
    "+jjb7nphEe+E-EEgHb22v1", 
    "\u5b88\u5854\u8005"
   ]
  }, 
  {
   "__tuple__": true, 
   "items": [
    "/2147483647", 
    9, 
    "+jo7UHphEe+t4UEgHb22v4", 
    "\u91ce\u5916"
   ]
  }, 
  {
   "__tuple__": true, 
   "items": [
    "/2147483647/+jo7UHphEe+t4UEgHb22v4", 
    0, 
    "+jo7UXphEe+d90EgHb22v4", 
    "\u5c71\u8d3c"
   ]
  }, 
  {
   "__tuple__": true, 
   "items": [
    "/2147483647", 
    10, 
    "+kP98HphEe+uzkEgHb22v0", 
    "\u526f\u672c\u533a\u57df"
   ]
  }, 
  {
   "__tuple__": true, 
   "items": [
    "/2147483647/+kP98HphEe+uzkEgHb22v0", 
    0, 
    "+kP98XphEe+VvEEgHb22v0", 
    "\u56db\u5723\u8bd5\u70bc"
   ]
  }, 
  {
   "__tuple__": true, 
   "items": [
    "/2147483647/+kP98HphEe+uzkEgHb22v0", 
    1, 
    "+kmFo3phEe+kZkEgHb22v4", 
    "\u7cbe\u7075\u4e4b\u68ee"
   ]
  }, 
  {
   "__tuple__": true, 
   "items": [
    "/2147483647/+kP98HphEe+uzkEgHb22v0", 
    2, 
    "+k8DFnphEe+zx0EgHb22v0", 
    "\u6df7\u6c8c\u6218\u573a"
   ]
  }, 
  {
   "__tuple__": true, 
   "items": [
    "/2147483647/+kP98HphEe+uzkEgHb22v0", 
    3, 
    "+leNU3phEe+4uEEgHb22vz", 
    "\u5927\u5730\u4e4b\u6b87"
   ]
  }, 
  {
   "__tuple__": true, 
   "items": [
    "/2147483647/+kP98HphEe+uzkEgHb22v0", 
    4, 
    "+l6RPXphEe+EYUEgHb22v3", 
    "\u6d77\u5996"
   ]
  }, 
  {
   "__tuple__": true, 
   "items": [
    "/2147483647/+kP98HphEe+uzkEgHb22v0", 
    5, 
    "+mQOlXphEe+q4kEgHb22v2", 
    "\u534a\u4eba\u9a6c\u730e\u573a"
   ]
  }
 ], 
 "d": {
  "134274912": {
   "__tuple__": true, 
   "items": [
    "-S46EXZrEe+W3M9IC1V7u4", 
    0
   ]
  }, 
  "134241735": {
   "__tuple__": true, 
   "items": [
    "-S46EXZrEe+W3M9IC1V7u4", 
    1
   ]
  }, 
  "134219749": {
   "__tuple__": true, 
   "items": [
    "-S46EXZrEe+W3M9IC1V7u4", 
    2
   ]
  }, 
  "134240279": {
   "__tuple__": true, 
   "items": [
    "-S46EXZrEe+W3M9IC1V7u4", 
    3
   ]
  }, 
  "134222661": {
   "__tuple__": true, 
   "items": [
    "-S46EXZrEe+W3M9IC1V7u4", 
    4
   ]
  }, 
  "134275571": {
   "__tuple__": true, 
   "items": [
    "-S46EXZrEe+W3M9IC1V7u4", 
    5
   ]
  }, 
  "134265083": {
   "__tuple__": true, 
   "items": [
    "-S46EXZrEe+W3M9IC1V7u4", 
    6
   ]
  }, 
  "134240721": {
   "__tuple__": true, 
   "items": [
    "-S46EXZrEe+W3M9IC1V7u4", 
    7
   ]
  }, 
  "134272952": {
   "__tuple__": true, 
   "items": [
    "-S46EXZrEe+W3M9IC1V7u4", 
    8
   ]
  }, 
  "134240731": {
   "__tuple__": true, 
   "items": [
    "-S46EXZrEe+W3M9IC1V7u4", 
    9
   ]
  }, 
  "134242658": {
   "__tuple__": true, 
   "items": [
    "-S46EXZrEe+W3M9IC1V7u4", 
    10
   ]
  }, 
  "134269059": {
   "__tuple__": true, 
   "items": [
    "-S46EXZrEe+W3M9IC1V7u4", 
    11
   ]
  }, 
  "134279795": {
   "__tuple__": true, 
   "items": [
    "-S46EXZrEe+W3M9IC1V7u4", 
    12
   ]
  }, 
  "134230062": {
   "__tuple__": true, 
   "items": [
    "-S46EXZrEe+W3M9IC1V7u4", 
    13
   ]
  }, 
  "134218426": {
   "__tuple__": true, 
   "items": [
    "-S46EXZrEe+W3M9IC1V7u4", 
    14
   ]
  }, 
  "134279196": {
   "__tuple__": true, 
   "items": [
    "-S46EXZrEe+W3M9IC1V7u4", 
    15
   ]
  }, 
  "134242543": {
   "__tuple__": true, 
   "items": [
    "-S46EXZrEe+W3M9IC1V7u4", 
    16
   ]
  }, 
  "134257382": {
   "__tuple__": true, 
   "items": [
    "-S46EXZrEe+W3M9IC1V7u4", 
    17
   ]
  }, 
  "134220068": {
   "__tuple__": true, 
   "items": [
    "-S46EXZrEe+W3M9IC1V7u4", 
    18
   ]
  }, 
  "134224181": {
   "__tuple__": true, 
   "items": [
    "-S46EXZrEe+W3M9IC1V7u4", 
    19
   ]
  }, 
  "134238059": {
   "__tuple__": true, 
   "items": [
    "-S46EXZrEe+W3M9IC1V7u4", 
    20
   ]
  }, 
  "134265927": {
   "__tuple__": true, 
   "items": [
    "-S46EXZrEe+W3M9IC1V7u4", 
    21
   ]
  }, 
  "134253585": {
   "__tuple__": true, 
   "items": [
    "-S46EXZrEe+W3M9IC1V7u4", 
    22
   ]
  }, 
  "134250762": {
   "__tuple__": true, 
   "items": [
    "-S46EXZrEe+W3M9IC1V7u4", 
    23
   ]
  }, 
  "134228855": {
   "__tuple__": true, 
   "items": [
    "-S46EXZrEe+W3M9IC1V7u4", 
    24
   ]
  }, 
  "134228282": {
   "__tuple__": true, 
   "items": [
    "-S46EXZrEe+W3M9IC1V7u4", 
    25
   ]
  }, 
  "134226901": {
   "__tuple__": true, 
   "items": [
    "-S46EXZrEe+W3M9IC1V7u4", 
    26
   ]
  }, 
  "134280096": {
   "__tuple__": true, 
   "items": [
    "-S46EXZrEe+W3M9IC1V7u4", 
    27
   ]
  }, 
  "134233553": {
   "__tuple__": true, 
   "items": [
    "-S46EXZrEe+W3M9IC1V7u4", 
    28
   ]
  }, 
  "134259608": {
   "__tuple__": true, 
   "items": [
    "-S46EXZrEe+W3M9IC1V7u4", 
    29
   ]
  }, 
  "134224570": {
   "__tuple__": true, 
   "items": [
    "-S46EXZrEe+W3M9IC1V7u4", 
    30
   ]
  }, 
  "201339863": {
   "__tuple__": true, 
   "items": [
    2147483647, 
    2
   ]
  }, 
  "134241051": {
   "__tuple__": true, 
   "items": [
    2147483647, 
    3
   ]
  }, 
  "134237181": {
   "__tuple__": true, 
   "items": [
    "OmlnWXc0Ee+5MLVju2zWk5", 
    0
   ]
  }, 
  "134233243": {
   "__tuple__": true, 
   "items": [
    "+dRcfXphEe+GV0EgHb22v9", 
    0
   ]
  }, 
  "134236912": {
   "__tuple__": true, 
   "items": [
    "+dRcfXphEe+GV0EgHb22v9", 
    1
   ]
  }, 
  "134274424": {
   "__tuple__": true, 
   "items": [
    "+dRcfXphEe+GV0EgHb22v9", 
    2
   ]
  }, 
  "134235951": {
   "__tuple__": true, 
   "items": [
    "+dRcfXphEe+GV0EgHb22v9", 
    3
   ]
  }, 
  "134281027": {
   "__tuple__": true, 
   "items": [
    "+dRcfXphEe+GV0EgHb22v9", 
    4
   ]
  }, 
  "134223394": {
   "__tuple__": true, 
   "items": [
    "+duHXnphEe+UlEEgHb22v9", 
    0
   ]
  }, 
  "134279562": {
   "__tuple__": true, 
   "items": [
    "+duHXnphEe+UlEEgHb22v9", 
    1
   ]
  }, 
  "134258485": {
   "__tuple__": true, 
   "items": [
    "+duHXnphEe+UlEEgHb22v9", 
    2
   ]
  }, 
  "134245455": {
   "__tuple__": true, 
   "items": [
    "+duHXnphEe+UlEEgHb22v9", 
    3
   ]
  }, 
  "134252384": {
   "__tuple__": true, 
   "items": [
    "+duHXnphEe+UlEEgHb22v9", 
    4
   ]
  }, 
  "134225459": {
   "__tuple__": true, 
   "items": [
    "+duHXnphEe+UlEEgHb22v9", 
    5
   ]
  }, 
  "134235405": {
   "__tuple__": true, 
   "items": [
    "+duHXnphEe+UlEEgHb22v9", 
    6
   ]
  }, 
  "134232230": {
   "__tuple__": true, 
   "items": [
    "+duHXnphEe+UlEEgHb22v9", 
    7
   ]
  }, 
  "134225764": {
   "__tuple__": true, 
   "items": [
    "+duHXnphEe+UlEEgHb22v9", 
    8
   ]
  }, 
  "134222852": {
   "__tuple__": true, 
   "items": [
    "+duHXnphEe+UlEEgHb22v9", 
    9
   ]
  }, 
  "134280568": {
   "__tuple__": true, 
   "items": [
    "+duHXnphEe+UlEEgHb22v9", 
    10
   ]
  }, 
  "134233500": {
   "__tuple__": true, 
   "items": [
    "+duHXnphEe+UlEEgHb22v9", 
    11
   ]
  }, 
  "134280554": {
   "__tuple__": true, 
   "items": [
    "+duHXnphEe+UlEEgHb22v9", 
    12
   ]
  }, 
  "134264225": {
   "__tuple__": true, 
   "items": [
    "+duHXnphEe+UlEEgHb22v9", 
    13
   ]
  }, 
  "134278088": {
   "__tuple__": true, 
   "items": [
    "+duHXnphEe+UlEEgHb22v9", 
    14
   ]
  }, 
  "134248956": {
   "__tuple__": true, 
   "items": [
    "+duHXnphEe+UlEEgHb22v9", 
    15
   ]
  }, 
  "134259484": {
   "__tuple__": true, 
   "items": [
    "+duHXnphEe+UlEEgHb22v9", 
    16
   ]
  }, 
  "134263463": {
   "__tuple__": true, 
   "items": [
    "+duHXnphEe+UlEEgHb22v9", 
    17
   ]
  }, 
  "134243219": {
   "__tuple__": true, 
   "items": [
    "+duHXnphEe+UlEEgHb22v9", 
    18
   ]
  }, 
  "134238946": {
   "__tuple__": true, 
   "items": [
    "+duHXnphEe+UlEEgHb22v9", 
    19
   ]
  }, 
  "134278322": {
   "__tuple__": true, 
   "items": [
    "+duHXnphEe+UlEEgHb22v9", 
    20
   ]
  }, 
  "134270303": {
   "__tuple__": true, 
   "items": [
    "+duHXnphEe+UlEEgHb22v9", 
    21
   ]
  }, 
  "134261092": {
   "__tuple__": true, 
   "items": [
    "+duHXnphEe+UlEEgHb22v9", 
    22
   ]
  }, 
  "134251972": {
   "__tuple__": true, 
   "items": [
    "+duHXnphEe+UlEEgHb22v9", 
    23
   ]
  }, 
  "134274792": {
   "__tuple__": true, 
   "items": [
    "+fztLHphEe+GmEEgHb22v7", 
    0
   ]
  }, 
  "134241524": {
   "__tuple__": true, 
   "items": [
    "+fztLHphEe+GmEEgHb22v7", 
    1
   ]
  }, 
  "134228159": {
   "__tuple__": true, 
   "items": [
    "+fztLHphEe+GmEEgHb22v7", 
    2
   ]
  }, 
  "134256629": {
   "__tuple__": true, 
   "items": [
    "+fztLHphEe+GmEEgHb22v7", 
    3
   ]
  }, 
  "134271653": {
   "__tuple__": true, 
   "items": [
    "+fztLHphEe+GmEEgHb22v7", 
    4
   ]
  }, 
  "134269084": {
   "__tuple__": true, 
   "items": [
    "+fztLHphEe+GmEEgHb22v7", 
    5
   ]
  }, 
  "134227042": {
   "__tuple__": true, 
   "items": [
    "+fztLHphEe+GmEEgHb22v7", 
    6
   ]
  }, 
  "134244781": {
   "__tuple__": true, 
   "items": [
    "+fztLHphEe+GmEEgHb22v7", 
    7
   ]
  }, 
  "134277952": {
   "__tuple__": true, 
   "items": [
    "+fztLHphEe+GmEEgHb22v7", 
    8
   ]
  }, 
  "134249744": {
   "__tuple__": true, 
   "items": [
    "+fztLHphEe+GmEEgHb22v7", 
    9
   ]
  }, 
  "134257407": {
   "__tuple__": true, 
   "items": [
    "+fztLHphEe+GmEEgHb22v7", 
    10
   ]
  }, 
  "134266958": {
   "__tuple__": true, 
   "items": [
    "+fztLHphEe+GmEEgHb22v7", 
    11
   ]
  }, 
  "134241515": {
   "__tuple__": true, 
   "items": [
    "+fztLHphEe+GmEEgHb22v7", 
    12
   ]
  }, 
  "134233228": {
   "__tuple__": true, 
   "items": [
    "+fztLHphEe+GmEEgHb22v7", 
    13
   ]
  }, 
  "134218816": {
   "__tuple__": true, 
   "items": [
    "+fztLHphEe+GmEEgHb22v7", 
    14
   ]
  }, 
  "134256319": {
   "__tuple__": true, 
   "items": [
    "+fztLHphEe+GmEEgHb22v7", 
    15
   ]
  }, 
  "134241904": {
   "__tuple__": true, 
   "items": [
    "+fztLHphEe+GmEEgHb22v7", 
    16
   ]
  }, 
  "134266810": {
   "__tuple__": true, 
   "items": [
    "+fztLHphEe+GmEEgHb22v7", 
    17
   ]
  }, 
  "134271435": {
   "__tuple__": true, 
   "items": [
    "+fztLHphEe+GmEEgHb22v7", 
    18
   ]
  }, 
  "134265840": {
   "__tuple__": true, 
   "items": [
    "+fztLHphEe+GmEEgHb22v7", 
    19
   ]
  }, 
  "134267996": {
   "__tuple__": true, 
   "items": [
    "+fztLHphEe+GmEEgHb22v7", 
    20
   ]
  }, 
  "134248011": {
   "__tuple__": true, 
   "items": [
    "+fztLHphEe+GmEEgHb22v7", 
    21
   ]
  }, 
  "134271519": {
   "__tuple__": true, 
   "items": [
    "+fztLHphEe+GmEEgHb22v7", 
    22
   ]
  }, 
  "134279410": {
   "__tuple__": true, 
   "items": [
    "+fztLHphEe+GmEEgHb22v7", 
    23
   ]
  }, 
  "134236248": {
   "__tuple__": true, 
   "items": [
    "+fztLHphEe+GmEEgHb22v7", 
    24
   ]
  }, 
  "134266684": {
   "__tuple__": true, 
   "items": [
    "+fztLHphEe+GmEEgHb22v7", 
    25
   ]
  }, 
  "134244894": {
   "__tuple__": true, 
   "items": [
    "+fztLHphEe+GmEEgHb22v7", 
    26
   ]
  }, 
  "134253826": {
   "__tuple__": true, 
   "items": [
    "+iKYIXphEe+KfEEgHb22vy", 
    0
   ]
  }, 
  "134282832": {
   "__tuple__": true, 
   "items": [
    "+iKYIXphEe+KfEEgHb22vy", 
    1
   ]
  }, 
  "134233140": {
   "__tuple__": true, 
   "items": [
    "+iVW3XphEe+0jUEgHb22vy", 
    0
   ]
  }, 
  "134235150": {
   "__tuple__": true, 
   "items": [
    "+ia2NHphEe+wp0EgHb22v+", 
    0
   ]
  }, 
  "134228358": {
   "__tuple__": true, 
   "items": [
    "+ia2NHphEe+wp0EgHb22v+", 
    1
   ]
  }, 
  "134226329": {
   "__tuple__": true, 
   "items": [
    "+ia2NHphEe+wp0EgHb22v+", 
    2
   ]
  }, 
  "134255294": {
   "__tuple__": true, 
   "items": [
    "+ir7V3phEe+4H0EgHb22vy", 
    0
   ]
  }, 
  "134270845": {
   "__tuple__": true, 
   "items": [
    "+ir7V3phEe+4H0EgHb22vy", 
    1
   ]
  }, 
  "134262453": {
   "__tuple__": true, 
   "items": [
    "+i26DXphEe+yhkEgHb22vw", 
    0
   ]
  }, 
  "134237199": {
   "__tuple__": true, 
   "items": [
    "+i26DXphEe+yhkEgHb22vw", 
    1
   ]
  }, 
  "134263542": {
   "__tuple__": true, 
   "items": [
    "+jB4zXphEe+Vb0EgHb22v7", 
    0
   ]
  }, 
  "134271237": {
   "__tuple__": true, 
   "items": [
    "+jB4zXphEe+Vb0EgHb22v7", 
    1
   ]
  }, 
  "134246184": {
   "__tuple__": true, 
   "items": [
    "+jNek3phEe+4HkEgHb22v-", 
    0
   ]
  }, 
  "134242662": {
   "__tuple__": true, 
   "items": [
    "+jNek3phEe+4HkEgHb22v-", 
    1
   ]
  }, 
  "134264737": {
   "__tuple__": true, 
   "items": [
    "+jYdTnphEe+4EkEgHb22vw", 
    0
   ]
  }, 
  "134246544": {
   "__tuple__": true, 
   "items": [
    "+jYdTnphEe+4EkEgHb22vw", 
    1
   ]
  }, 
  "134226962": {
   "__tuple__": true, 
   "items": [
    "+jjb7nphEe+E-EEgHb22v1", 
    0
   ]
  }, 
  "134266285": {
   "__tuple__": true, 
   "items": [
    "+jo7UXphEe+d90EgHb22v4", 
    0
   ]
  }, 
  "134254340": {
   "__tuple__": true, 
   "items": [
    "+jo7UXphEe+d90EgHb22v4", 
    1
   ]
  }, 
  "134249318": {
   "__tuple__": true, 
   "items": [
    "+jo7UXphEe+d90EgHb22v4", 
    2
   ]
  }, 
  "134238943": {
   "__tuple__": true, 
   "items": [
    "+jo7UXphEe+d90EgHb22v4", 
    3
   ]
  }, 
  "134281441": {
   "__tuple__": true, 
   "items": [
    "+jo7UXphEe+d90EgHb22v4", 
    4
   ]
  }, 
  "134266033": {
   "__tuple__": true, 
   "items": [
    "+jo7UXphEe+d90EgHb22v4", 
    5
   ]
  }, 
  "134280049": {
   "__tuple__": true, 
   "items": [
    "+jo7UXphEe+d90EgHb22v4", 
    6
   ]
  }, 
  "134283209": {
   "__tuple__": true, 
   "items": [
    "+kP98XphEe+VvEEgHb22v0", 
    0
   ]
  }, 
  "134224636": {
   "__tuple__": true, 
   "items": [
    "+kP98XphEe+VvEEgHb22v0", 
    1
   ]
  }, 
  "134282716": {
   "__tuple__": true, 
   "items": [
    "+kP98XphEe+VvEEgHb22v0", 
    2
   ]
  }, 
  "134248965": {
   "__tuple__": true, 
   "items": [
    "+kP98XphEe+VvEEgHb22v0", 
    3
   ]
  }, 
  "134217952": {
   "__tuple__": true, 
   "items": [
    "+kmFo3phEe+kZkEgHb22v4", 
    0
   ]
  }, 
  "134231279": {
   "__tuple__": true, 
   "items": [
    "+kmFo3phEe+kZkEgHb22v4", 
    1
   ]
  }, 
  "134275786": {
   "__tuple__": true, 
   "items": [
    "+kmFo3phEe+kZkEgHb22v4", 
    2
   ]
  }, 
  "134237714": {
   "__tuple__": true, 
   "items": [
    "+kmFo3phEe+kZkEgHb22v4", 
    3
   ]
  }, 
  "134247767": {
   "__tuple__": true, 
   "items": [
    "+k8DFnphEe+zx0EgHb22v0", 
    0
   ]
  }, 
  "134265394": {
   "__tuple__": true, 
   "items": [
    "+k8DFnphEe+zx0EgHb22v0", 
    1
   ]
  }, 
  "134225004": {
   "__tuple__": true, 
   "items": [
    "+k8DFnphEe+zx0EgHb22v0", 
    2
   ]
  }, 
  "134254288": {
   "__tuple__": true, 
   "items": [
    "+k8DFnphEe+zx0EgHb22v0", 
    3
   ]
  }, 
  "134232943": {
   "__tuple__": true, 
   "items": [
    "+k8DFnphEe+zx0EgHb22v0", 
    4
   ]
  }, 
  "134279023": {
   "__tuple__": true, 
   "items": [
    "+k8DFnphEe+zx0EgHb22v0", 
    5
   ]
  }, 
  "134231508": {
   "__tuple__": true, 
   "items": [
    "+leNU3phEe+4uEEgHb22vz", 
    0
   ]
  }, 
  "134234521": {
   "__tuple__": true, 
   "items": [
    "+leNU3phEe+4uEEgHb22vz", 
    1
   ]
  }, 
  "134226564": {
   "__tuple__": true, 
   "items": [
    "+leNU3phEe+4uEEgHb22vz", 
    2
   ]
  }, 
  "134254432": {
   "__tuple__": true, 
   "items": [
    "+leNU3phEe+4uEEgHb22vz", 
    3
   ]
  }, 
  "134230466": {
   "__tuple__": true, 
   "items": [
    "+leNU3phEe+4uEEgHb22vz", 
    4
   ]
  }, 
  "134274187": {
   "__tuple__": true, 
   "items": [
    "+l6RPXphEe+EYUEgHb22v3", 
    0
   ]
  }, 
  "134222698": {
   "__tuple__": true, 
   "items": [
    "+l6RPXphEe+EYUEgHb22v3", 
    1
   ]
  }, 
  "134279903": {
   "__tuple__": true, 
   "items": [
    "+l6RPXphEe+EYUEgHb22v3", 
    2
   ]
  }, 
  "134259741": {
   "__tuple__": true, 
   "items": [
    "+l6RPXphEe+EYUEgHb22v3", 
    3
   ]
  }, 
  "134251384": {
   "__tuple__": true, 
   "items": [
    "+mQOlXphEe+q4kEgHb22v2", 
    0
   ]
  }, 
  "134225461": {
   "__tuple__": true, 
   "items": [
    "+mQOlXphEe+q4kEgHb22v2", 
    1
   ]
  }, 
  "134275319": {
   "__tuple__": true, 
   "items": [
    "+mQOlXphEe+q4kEgHb22v2", 
    2
   ]
  }, 
  "134222350": {
   "__tuple__": true, 
   "items": [
    "+mQOlXphEe+q4kEgHb22v2", 
    3
   ]
  }, 
  "134263406": {
   "__tuple__": true, 
   "items": [
    "+mQOlXphEe+q4kEgHb22v2", 
    4
   ]
  }, 
  "134232031": {
   "__tuple__": true, 
   "items": [
    2147483647, 
    11
   ]
  }
 }
}